indica/__init__.py
indica/abstractio.py
indica/available_quantities.py
indica/configs/__init__.py
indica/configs/profilers/profiler_cubicspline.yaml
indica/configs/profilers/profiler_gauss.yaml
indica/configs/profilers/profiler_monospline.yaml
indica/configs/readers/__init__.py
indica/configs/readers/adasconf.py
indica/configs/readers/jetconf.py
indica/configs/readers/machineconf.py
indica/configs/readers/st40conf.py
indica/configs/readers/st40readerprocessorconf.py
indica/configs/workflows/bda/__init__.py
indica/configs/workflows/bda/ion_temperature_phantom_run.yaml
indica/configs/workflows/bda/model/default.yaml
indica/configs/workflows/bda/optimisation/bo.yaml
indica/configs/workflows/bda/optimisation/emcee.yaml
indica/configs/workflows/bda/plasma/default.yaml
indica/configs/workflows/bda/plasma/profiles/default.yaml
indica/configs/workflows/bda/plasma/settings/default.yaml
indica/configs/workflows/bda/plasma_profiler/default.yaml
indica/configs/workflows/bda/priors/__init__.py
indica/configs/workflows/bda/priors/default.yaml
indica/configs/workflows/bda/reader/filters/default.yaml
indica/configs/workflows/bda/reader/phantom.yaml
indica/configs/workflows/bda/test_bo.yaml
indica/configs/workflows/bda/test_emcee.yaml
indica/converters/__init__.py
indica/converters/abstractconverter.py
indica/converters/line_of_sight.py
indica/converters/spot_weightings.py
indica/converters/time.py
indica/converters/transect.py
indica/converters/trivial.py
indica/data/Data_Argon/Cascade.dat
indica/data/Data_Argon/ChargeRates.dat
indica/data/Data_Argon/CorAr.dat
indica/data/Data_Argon/DirectRates.dat
indica/data/Data_Argon/DirectRatesRmatr
indica/data/Data_Argon/InnerRates.dat
indica/data/Data_Argon/LiCollSatt.dat
indica/data/Data_Argon/RecombRates.dat
indica/data/Data_Argon/WXYZ_R-matrix.txt
indica/data/Data_Argon/n2dielsat.dat
indica/data/Data_Argon/n2lidielsat.dat
indica/data/Data_Argon/n3dielsat.dat
indica/data/Data_Argon/n4dielsat.dat
indica/data/Data_Argon/n5dielsat.dat
indica-0.1.22.dist-info/METADATA
indica-0.1.22.dist-info/WHEEL
indica-0.1.22.dist-info/licenses/LICENSE.md
indica-0.1.22.dist-info/RECORD
