Metadata-Version: 2.4
Name: indica
Version: 0.1.22
Summary: INtegrated DIagnostiC Analysis
License-Expression: GPL-3.0-or-later
License-File: LICENSE.md
Author: Marco Sertoli
Author-email: marco.sertoli@tokamakenergy.com
Maintainer: Evie Litherland-Smith
Maintainer-email: evie.litherland-smith@ukaea.uk
Requires-Python: >=3.9
Classifier: Programming Language :: Python :: 3
Classifier: Programming Language :: Python :: 3.9
Classifier: Programming Language :: Python :: 3.10
Classifier: Programming Language :: Python :: 3.11
Classifier: Programming Language :: Python :: 3.12
Requires-Dist: GitPython (>=3.1.41)
Requires-Dist: Pint (>=0.23)
Requires-Dist: bottleneck (==1.4.0)
Requires-Dist: corner (>=1.0)
Requires-Dist: dime_sampler (==1.0.0)
Requires-Dist: emcee (>=3.1.4)
Requires-Dist: flatdict (>=4.0.1)
Requires-Dist: freeqdsk (>=0.5.0)
Requires-Dist: hydra-core (>=1.3.1)
Requires-Dist: matplotlib (>=3.8.0)
Requires-Dist: mpmath (>=1.3.0)
Requires-Dist: netCDF4 (>=1.5.4)
Requires-Dist: numpy (==1.26.4)
Requires-Dist: pandas (==2.2.1)
Requires-Dist: periodictable (>=1.6.1)
Requires-Dist: prov (>=1.5.3)
Requires-Dist: pyyaml (>=6.0.1)
Requires-Dist: sal (>=1.2.2)
Requires-Dist: scikit-learn (>=1.3.0)
Requires-Dist: scikit-optimize (>=0.10.2)
Requires-Dist: scipy (>=1.9.2)
Requires-Dist: tqdm (>=4.65.0)
Requires-Dist: xarray (==2024.6.0)
Project-URL: Repository, https://github.com/indica-mcf/Indica
